README.txt
setup.cfg
setup.py
Extremes.egg-info/PKG-INFO
Extremes.egg-info/SOURCES.txt
Extremes.egg-info/dependency_links.txt
Extremes.egg-info/namespace_packages.txt
Extremes.egg-info/top_level.txt
peak/__init__.py
peak/util/__init__.py
peak/util/extremes.py