Metadata-Version: 1.0
Name: Extremes
Version: 1.1
Summary: Production-quality 'Min' and 'Max' objects (adapted from PEP 326)
Home-page: http://pypi.python.org/pypi/Extremes
Author: Phillip J. Eby
Author-email: peak@eby-sarna.com
License: PSF or ZPL
Platform: UNKNOWN
